ez_settings/__init__.py
ez_settings/ez_settings_base.py
ez_settings/ez_settings_py2.py
ez_settings/ez_settings_py3.py
ez_settings/singleton.py
ez_settings-1.2.0.dist-info/LICENSE
ez_settings-1.2.0.dist-info/METADATA
ez_settings-1.2.0.dist-info/WHEEL
ez_settings-1.2.0.dist-info/top_level.txt
ez_settings-1.2.0.dist-info/RECORD
