Metadata-Version: 2.1
Name: ez-settings
Version: 1.2.0
Summary: Easy settings module
Home-page: https://github.com/nielsvaes/ez_settings
Author: Niels Vaes
Author-email: nielsvaes@gmail.com
License: MIT
Platform: UNKNOWN
Classifier: Operating System :: OS Independent
License-File: LICENSE
